pymwemu-0.10.5.dist-info/METADATA
pymwemu-0.10.5.dist-info/WHEEL
pymwemu/__init__.py
pymwemu/pymwemu.cpython-313-x86_64-linux-gnu.so
pymwemu-0.10.5.dist-info/RECORD
